libPy2023_l/__init__.py
libPy2023_l/libPy2023_l.py
libPy2023_l-2023.3.231211.dist-info/METADATA
libPy2023_l-2023.3.231211.dist-info/WHEEL
libPy2023_l-2023.3.231211.dist-info/top_level.txt
libPy2023_l-2023.3.231211.dist-info/RECORD
