Metadata-Version: 2.1
Name: libPy2023-l
Version: 2023.3.231211
Summary: Librerías de propósito General
Home-page: https://github.com/Dexsys/libPy2023_l
Author: Ludwig R. Corales Marti
Author-email: dexsys@gmail.com
Classifier: Development Status :: 4 - Beta
Classifier: Intended Audience :: Developers
Classifier: Programming Language :: Python :: 3
Classifier: Programming Language :: Python :: 3.6
Classifier: Programming Language :: Python :: 3.7
Classifier: Topic :: Software Development
Classifier: License :: Free for non-commercial use
Classifier: Operating System :: OS Independent
Classifier: Natural Language :: Spanish
Requires-Python: ~=3.5
Requires-Dist: keyboard
Requires-Dist: pandas
Provides-Extra: dev
Requires-Dist: setuptools ; extra == 'dev'
Requires-Dist: wheel ; extra == 'dev'
Requires-Dist: twine ; extra == 'dev'
Requires-Dist: Sphinx ; extra == 'dev'
